code_butler/__about__.py
code_butler/__init__.py
code_butler/__main__.py
code_butler/cli/__init__.py
code_butler-0.0.1.dist-info/METADATA
code_butler-0.0.1.dist-info/WHEEL
code_butler-0.0.1.dist-info/entry_points.txt
code_butler-0.0.1.dist-info/licenses/LICENSE
code_butler-0.0.1.dist-info/RECORD
